napari_chatgpt/__init__.py
napari_chatgpt/_widget.py
napari_chatgpt/napari.yaml
napari_chatgpt/chat_server/__init__.py
napari_chatgpt/chat_server/chat_response.py
napari_chatgpt/chat_server/chat_server.py
napari_chatgpt/chat_server/demo/__init__.py
napari_chatgpt/chat_server/demo/chat_server_demo.py
napari_chatgpt/chat_server/static/OmegaLogoIcon.png
napari_chatgpt/chat_server/static/_tailwind.css
napari_chatgpt/chat_server/static/chat.js
napari_chatgpt/chat_server/static/marked-highlight.js
napari_chatgpt/chat_server/static/marked.min.js
napari_chatgpt/chat_server/static/prism.css
napari_chatgpt/chat_server/static/prism.js
napari_chatgpt/chat_server/static/sunlight-min.js
napari_chatgpt/chat_server/static/sunlight.dark.css
napari_chatgpt/chat_server/static/sunlight.python-min.js
napari_chatgpt/chat_server/static/tailwind.min.css
napari_chatgpt/chat_server/templates/index.html
napari_chatgpt/llm/__init__.py
napari_chatgpt/llm/litemind_api.py
napari_chatgpt/llm/llm.py
napari_chatgpt/llm/api_keys/__init__.py
napari_chatgpt/llm/api_keys/api_key.py
napari_chatgpt/llm/api_keys/api_key_vault.py
napari_chatgpt/llm/api_keys/api_key_vault_dialog.py
napari_chatgpt/llm/api_keys/demo/__init__.py
napari_chatgpt/llm/api_keys/demo/api_key_vault_dialog_demo.py
napari_chatgpt/llm/api_keys/test/__init__.py
napari_chatgpt/llm/api_keys/test/api_key_vault_test.py
napari_chatgpt/microplugin/__init__.py
napari_chatgpt/microplugin/microplugin_window.py
napari_chatgpt/microplugin/code_editor/__init__.py
napari_chatgpt/microplugin/code_editor/clickable_icon.py
napari_chatgpt/microplugin/code_editor/code_drop_send_widget.py
napari_chatgpt/microplugin/code_editor/code_snippet_editor_widget.py
napari_chatgpt/microplugin/code_editor/code_snippet_editor_window.py
napari_chatgpt/microplugin/code_editor/console_widget.py
napari_chatgpt/microplugin/code_editor/python_code_completer.py
napari_chatgpt/microplugin/code_editor/python_code_editor_manager.py
napari_chatgpt-2025.7.28.1.dist-info/METADATA
napari_chatgpt-2025.7.28.1.dist-info/WHEEL
napari_chatgpt-2025.7.28.1.dist-info/entry_points.txt
napari_chatgpt-2025.7.28.1.dist-info/licenses/LICENSE
napari_chatgpt-2025.7.28.1.dist-info/RECORD
