Metadata-Version: 2.4
Name: napari-chatgpt
Version: 2025.7.28.1
Summary: A napari plugin that brings an LLM-powered agent (Omega) to interactive image analysis.
Project-URL: Homepage, https://github.com/royerlab/napari-chatgpt
Project-URL: Issues, https://github.com/royerlab/napari-chatgpt/issues
Author-email: "Loic A. Royer" <royerloic@gmail.com>
License: 
License-File: LICENSE
Requires-Python: >=3.9
Requires-Dist: arbol
Requires-Dist: black
Requires-Dist: cryptography
Requires-Dist: ddgs>=9.4.3
Requires-Dist: fastapi
Requires-Dist: httpx
Requires-Dist: imageio[ffmpeg,pyav]
Requires-Dist: jedi
Requires-Dist: litemind[documents,rag,tables]>=2025.07.28.1
Requires-Dist: lxml
Requires-Dist: lxml-html-clean
Requires-Dist: magicgui
Requires-Dist: matplotlib
Requires-Dist: nbformat
Requires-Dist: notebook
Requires-Dist: numba
Requires-Dist: numpy
Requires-Dist: ome-zarr
Requires-Dist: qtawesome
Requires-Dist: qtpy
Requires-Dist: scikit-image
Requires-Dist: tabulate
Requires-Dist: uvicorn
Requires-Dist: websockets
Requires-Dist: xarray
Provides-Extra: testing
Requires-Dist: napari; extra == 'testing'
Requires-Dist: pyqt5; extra == 'testing'
Requires-Dist: pytest; extra == 'testing'
Requires-Dist: pytest-cov; extra == 'testing'
Requires-Dist: pytest-qt; extra == 'testing'
Requires-Dist: tox; extra == 'testing'
